dictionary/__init__.py
dictionary/dictionary.py
arda_guven_cs453_hw1-2.0.5.dist-info/METADATA
arda_guven_cs453_hw1-2.0.5.dist-info/WHEEL
arda_guven_cs453_hw1-2.0.5.dist-info/top_level.txt
arda_guven_cs453_hw1-2.0.5.dist-info/RECORD
